llmtoolset/__init__.py
llmtoolset/embeddings.py
llmtoolset/utils.py
llmtoolset-0.4.dist-info/LICENSE
llmtoolset-0.4.dist-info/METADATA
llmtoolset-0.4.dist-info/WHEEL
llmtoolset-0.4.dist-info/top_level.txt
llmtoolset-0.4.dist-info/RECORD
