Metadata-Version: 2.1
Name: llmtoolset
Version: 0.4
Summary: Tools using ollama and torch that are easy and nice to have for working with local LLMs
Author: Matthew Sanchez
Author-email: 
Classifier: Programming Language :: Python :: 3
Classifier: License :: OSI Approved :: MIT License
Classifier: Operating System :: OS Independent
Requires-Python: >=3.10
License-File: LICENSE
Requires-Dist: chatollama
Requires-Dist: sentence-transformers
